k2pipe/__init__.py
k2pipe/mypipe.py
k2pipe/pipe.py
k2pipe/features/__init__.py
k2pipe/features/feature_utils.py
k2pipe-0.2.6.dist-info/METADATA
k2pipe-0.2.6.dist-info/WHEEL
k2pipe-0.2.6.dist-info/top_level.txt
k2pipe-0.2.6.dist-info/RECORD
