Metadata-Version: 2.4
Name: k2pipe
Version: 0.2.6
Summary: k2pipe
Home-page: https://www.k2data.com.cn
Author: K2data
Author-email: admin@k2data.com.cn
Classifier: Development Status :: 3 - Alpha
Classifier: Intended Audience :: Developers
Classifier: Programming Language :: Python :: 3
Classifier: Programming Language :: Python :: 3.8
Classifier: Programming Language :: Python :: 3.9
Classifier: Programming Language :: Python :: 3.10
Classifier: Operating System :: OS Independent
Classifier: Topic :: Software Development :: Libraries
Requires-Python: >=3.8
Requires-Dist: pandas
Requires-Dist: numexpr
Requires-Dist: loguru
Requires-Dist: graphviz
Requires-Dist: pytest
Requires-Dist: pytest-mock
Requires-Dist: pytest-cov
Dynamic: author
Dynamic: author-email
Dynamic: classifier
Dynamic: description
Dynamic: description-content-type
Dynamic: home-page
Dynamic: requires-dist
Dynamic: requires-python
Dynamic: summary
